gravomg_bindings.pypy310-pp73-x86_64-linux-gnu.so
gravomg/core.py
gravomg/util.py
gravomg/__init__.py
gravomg-0.0.4.dist-info/METADATA
gravomg-0.0.4.dist-info/top_level.txt
gravomg-0.0.4.dist-info/LICENSE
gravomg-0.0.4.dist-info/RECORD
gravomg-0.0.4.dist-info/WHEEL
