Metadata-Version: 2.1
Name: gravomg
Version: 0.0.4
Summary: Gravo MG: A Fast Geometric Multigrid Method for Curved Surfaces
Home-page: https://github.com/rubenwiersma/gravo_mg_python
Author: Ruben Wiersma and Ahmad Nasikun
Author-email: rubenwiersma@gmail.com
License: MIT
Project-URL: Bug Tracker, https://github.com/rubenwiersma/gravo_mg/issues
Classifier: Programming Language :: Python :: 3
Classifier: License :: OSI Approved :: Apache Software License
Classifier: Operating System :: OS Independent
License-File: LICENSE
Requires-Dist: numpy
Requires-Dist: scipy
